sourcepy/__about__.py
sourcepy/__init__.py
sourcepy/casters.py
sourcepy/loaders.py
sourcepy/parsers.py
sourcepy/run.py
sourcepy/source.py
sourcepy-0.1.0.dist-info/METADATA
sourcepy-0.1.0.dist-info/WHEEL
sourcepy-0.1.0.dist-info/licenses/LICENSE
sourcepy-0.1.0.dist-info/RECORD
