Metadata-Version: 2.1
Name: sourcepy
Version: 0.1.0
Summary: Source python files right from the terminal
Project-URL: Documentation, https://github.com/unknown/sourcepy#readme
Project-URL: Issues, https://github.com/unknown/sourcepy/issues
Project-URL: Source, https://github.com/unknown/sourcepy
Author-email: Dave Chevell <chevell@gmail.com>
License-Expression: MIT
License-File: LICENSE
Keywords: bash,shell,zsh
Classifier: Development Status :: 4 - Beta
Classifier: Programming Language :: Python
Classifier: Programming Language :: Python :: 3.8
Classifier: Programming Language :: Python :: 3.9
Classifier: Programming Language :: Python :: 3.10
Classifier: Programming Language :: Python :: 3.11
Classifier: Programming Language :: Python :: 3.12
Classifier: Programming Language :: Python :: Implementation :: CPython
Classifier: Programming Language :: Python :: Implementation :: PyPy
Requires-Python: >=3.8
